docstrange/WEB_INTERFACE.md
docstrange/__init__.py
docstrange/cli.py
docstrange/config.py
docstrange/exceptions.py
docstrange/extractor.py
docstrange/result.py
docstrange/web_app.py
docstrange/__pycache__/__init__.cpython-311.pyc
docstrange/__pycache__/cli.cpython-311.pyc
docstrange/__pycache__/config.cpython-311.pyc
docstrange/__pycache__/exceptions.cpython-311.pyc
docstrange/__pycache__/extractor.cpython-311.pyc
docstrange/__pycache__/result.cpython-311.pyc
docstrange/__pycache__/web_app.cpython-311.pyc
docstrange/pipeline/__init__.py
docstrange/pipeline/layout_detector.py
docstrange/pipeline/model_downloader.py
docstrange/pipeline/nanonets_processor.py
docstrange/pipeline/neural_document_processor.py
docstrange/pipeline/ocr_service.py
docstrange/pipeline/__pycache__/__init__.cpython-311.pyc
docstrange/pipeline/__pycache__/layout_detector.cpython-311.pyc
docstrange/pipeline/__pycache__/model_downloader.cpython-311.pyc
docstrange/pipeline/__pycache__/neural_document_processor.cpython-311.pyc
docstrange/pipeline/__pycache__/ocr_service.cpython-311.pyc
docstrange/processors/__init__.py
docstrange/processors/base.py
docstrange/processors/cloud_processor.py
docstrange/processors/docx_processor.py
docstrange/processors/excel_processor.py
docstrange/processors/gpu_processor.py
docstrange/processors/html_processor.py
docstrange/processors/image_processor.py
docstrange/processors/pdf_processor.py
docstrange/processors/pptx_processor.py
docstrange/processors/txt_processor.py
docstrange/processors/url_processor.py
docstrange/processors/__pycache__/__init__.cpython-311.pyc
docstrange/processors/__pycache__/base.cpython-311.pyc
docstrange/processors/__pycache__/cloud_processor.cpython-311.pyc
docstrange/processors/__pycache__/docx_processor.cpython-311.pyc
docstrange/processors/__pycache__/excel_processor.cpython-311.pyc
docstrange/processors/__pycache__/gpu_processor.cpython-311.pyc
docstrange/processors/__pycache__/html_processor.cpython-311.pyc
docstrange-1.1.7.dist-info/licenses/LICENSE
docstrange-1.1.7.dist-info/METADATA
docstrange-1.1.7.dist-info/WHEEL
docstrange-1.1.7.dist-info/entry_points.txt
docstrange-1.1.7.dist-info/top_level.txt
docstrange-1.1.7.dist-info/RECORD
